{
  "Id": "f586042c-8b26-4c8e-8b76-e8aa2e17421f",
  "Result": {
    "Date": "2026-05-03T00:00:00+03:00",
    "PersonnelNumber": "1000000",
    "FactoryCode": "00005",
    "FactoryName": "Factory5",
    "TechnicalPlaces": [
      {
        "Code": 999,
        "ParentCode": 0,
        "ModelCode": "",
        "Name": "Формувальний підрозділ",
        "FactoryCode": "00005",
        "FactoryName": "Factory5",
        "DepartmentCode": 50915,
        "DepartmentName": "Відділ головного механіка",
        "TechnicalPlaces": [
          {
            "Code": 3333,
            "ParentCode": 999,
            "ModelCode": "Т00000000000001",
            "Name": "Стенд для виготовлення продукції",
            "FactoryCode": "00005",
            "FactoryName": "Factory5",
            "DepartmentCode": 50915,
            "DepartmentName": "Відділ головного механіка",
            "TechnicalPlaces": null,
            "Equipments": [
              {
                "Code": "BBB1062",
                "TechPlaceCode": 3333,
                "FactoryCode": "00005",
                "TypeCode": "0390",
                "TypeName": "Стенд для виготовлення продукції",
                "ModelCode": "Т00000000000001",
                "Name": "Формувальний стенд 0",
                "FullName": "Стенд для виготовлення продукції",
                "Marking": "",
                "CriticalityLevel": "B2",
                "MonitorDateStart": "2025-11-03T00:00:00+00:00",
                "MonitorFrequencyCode": 5,
                "MonitorFrequency": "1 раз на півроку",
                "QrCode": null,
                "OdometerDataRequired": false,
                "MonitoringTasks": [
                  {
                    "Code": 1011111,
                    "EquipmentCode": "BBB1062",
                    "TechPlaceCode": 3333,
                    "TechPlaceParentCode": 999,
                    "ModelCode": "Т00000000000001",
                    "ModelName": "Стенд для виготовлення продукції",
                    "CharacteristicCode": 166,
                    "CharacteristicName": "Відсутність лінійного видовження стенду",
                    "UnitName": "Візуально",
                    "Value": 0,
                    "IsBool": true,
                    "PlanDate": "2026-05-03T00:00:00+00:00",
                    "FactDate": "0001-01-01T00:00:00+00:00",
                    "EquipmentTypeCode": "0390",
                    "EquipmentTypeName": "Стенд для виготовлення продукції",
                    "Description": "",
                    "FactoryCode": "00005",
                    "DepartmentCode": 50915,
                    "ModifiedBy": null,
                    "ShouldFilterByDepartmentCode": true,
                    "ValueRange": [
                      {
                        "Code": 20835,
                        "MonitoringTaskCode": 1011111,
                        "EquipmentCode": "",
                        "ReferenceCode": 3155,
                        "CharacteristicCode": 166,
                        "MinValue": 1,
                        "MaxValue": 1,
                        "NormalValue": 1,
                        "ValueCode": 5,
                        "ValueName": "Тривога",
                        "CategoryCode": "4",
                        "CategoryName": "Аварійність",
                        "Status": ""
                      },
                      {
                        "Code": 16124,
                        "MonitoringTaskCode": 1011111,
                        "EquipmentCode": "",
                        "ReferenceCode": 3155,
                        "CharacteristicCode": 166,
                        "MinValue": -1,
                        "MaxValue": -1,
                        "NormalValue": 5,
                        "ValueCode": 4,
                        "ValueName": "Норма",
                        "CategoryCode": "1IM",
                        "CategoryName": "Поліпшення",
                        "Status": ""
                      }
                    ]
                  },
                  {
                    "Code": 1022222,
                    "EquipmentCode": "BBB1062",
                    "TechPlaceCode": 3333,
                    "TechPlaceParentCode": 999,
                    "ModelCode": "Т00000000000001",
                    "ModelName": "Стенд для виготовлення продукції",
                    "CharacteristicCode": 1143,
                    "CharacteristicName": "Наявність порізів від пили поперечного різу",
                    "UnitName": "Візуально",
                    "Value": 0,
                    "IsBool": true,
                    "PlanDate": "2026-05-03T00:00:00+00:00",
                    "FactDate": "0001-01-01T00:00:00+00:00",
                    "EquipmentTypeCode": "0390",
                    "EquipmentTypeName": "Стенд для виготовлення продукції",
                    "Description": "",
                    "FactoryCode": "00005",
                    "DepartmentCode": 50915,
                    "ModifiedBy": null,
                    "ShouldFilterByDepartmentCode": true,
                    "ValueRange": [
                      {
                        "Code": 20836,
                        "MonitoringTaskCode": 1022222,
                        "EquipmentCode": "",
                        "ReferenceCode": 3156,
                        "CharacteristicCode": 1143,
                        "MinValue": 1,
                        "MaxValue": 1,
                        "NormalValue": 1,
                        "ValueCode": 5,
                        "ValueName": "Тривога",
                        "CategoryCode": "4",
                        "CategoryName": "Аварійність",
                        "Status": ""
                      },
                      {
                        "Code": 16125,
                        "MonitoringTaskCode": 1022222,
                        "EquipmentCode": "",
                        "ReferenceCode": 3156,
                        "CharacteristicCode": 1143,
                        "MinValue": -1,
                        "MaxValue": -1,
                        "NormalValue": 5,
                        "ValueCode": 4,
                        "ValueName": "Норма",
                        "CategoryCode": "1IM",
                        "CategoryName": "Поліпшення",
                        "Status": ""
                      }
                    ]
                  }
                ],
                "MaintenanceTasks": null,
                "RepairTasks": null
              }
            ]
          }
        ],
        "Equipments": null
      },
      {
        "Code": 933,
        "ParentCode": 0,
        "ModelCode": "",
        "Name": "Котельня газова",
        "FactoryCode": "00005",
        "FactoryName": "Factory5",
        "DepartmentCode": 50915,
        "DepartmentName": "Відділ головного механіка",
        "TechnicalPlaces": [
          {
            "Code": 2550,
            "ParentCode": 933,
            "ModelCode": "Т00000000400002",
            "Name": "Пункт р.",
            "FactoryCode": "00005",
            "FactoryName": "Factory5",
            "DepartmentCode": 50915,
            "DepartmentName": "Відділ головного механіка",
            "TechnicalPlaces": null,
            "Equipments": [
              {
                "Code": "BBB797",
                "TechPlaceCode": 2550,
                "FactoryCode": "00005",
                "TypeCode": "0349",
                "TypeName": "Пункт р.",
                "ModelCode": "Т00000000400002",
                "Name": "Пункт р.ш.",
                "FullName": "Пункт р.ш.",
                "Marking": "ШРП",
                "CriticalityLevel": "B2",
                "MonitorDateStart": "2025-03-03T00:00:00+00:00",
                "MonitorFrequencyCode": 3,
                "MonitorFrequency": "Щомісяця",
                "QrCode": null,
                "OdometerDataRequired": false,
                "MonitoringTasks": [
                  {
                    "Code": 1016533,
                    "EquipmentCode": "BBB797",
                    "TechPlaceCode": 2550,
                    "TechPlaceParentCode": 933,
                    "ModelCode": "Т00000000400002",
                    "ModelName": "Пункт р.ш.",
                    "CharacteristicCode": 618,
                    "CharacteristicName": "Наявність викиду газу",
                    "UnitName": "Візуально",
                    "Value": 0,
                    "IsBool": true,
                    "PlanDate": "2026-05-03T00:00:00+00:00",
                    "FactDate": "0001-01-01T00:00:00+00:00",
                    "EquipmentTypeCode": "0349",
                    "EquipmentTypeName": "Пункт р.ш.",
                    "Description": "",
                    "FactoryCode": "00005",
                    "DepartmentCode": 50915,
                    "ModifiedBy": null,
                    "ShouldFilterByDepartmentCode": true,
                    "ValueRange": [
                      {
                        "Code": 20813,
                        "MonitoringTaskCode": 1016533,
                        "EquipmentCode": "",
                        "ReferenceCode": 3132,
                        "CharacteristicCode": 618,
                        "MinValue": 1,
                        "MaxValue": 1,
                        "NormalValue": 1,
                        "ValueCode": 5,
                        "ValueName": "Тривога",
                        "CategoryCode": "4",
                        "CategoryName": "Аварійність",
                        "Status": ""
                      },
                      {
                        "Code": 16102,
                        "MonitoringTaskCode": 1016533,
                        "EquipmentCode": "",
                        "ReferenceCode": 3132,
                        "CharacteristicCode": 618,
                        "MinValue": -1,
                        "MaxValue": -1,
                        "NormalValue": 5,
                        "ValueCode": 4,
                        "ValueName": "Норма",
                        "CategoryCode": "1IM",
                        "CategoryName": "Поліпшення",
                        "Status": ""
                      }
                    ]
                  },
                  {
                    "Code": 1016534,
                    "EquipmentCode": "BBB797",
                    "TechPlaceCode": 2550,
                    "TechPlaceParentCode": 933,
                    "ModelCode": "Т00000000400002",
                    "ModelName": "Пункт р.ш.",
                    "CharacteristicCode": 661,
                    "CharacteristicName": "Наявність витоку газу",
                    "UnitName": "Візуально",
                    "Value": 0,
                    "IsBool": true,
                    "PlanDate": "2026-05-03T00:00:00+00:00",
                    "FactDate": "0001-01-01T00:00:00+00:00",
                    "EquipmentTypeCode": "0349",
                    "EquipmentTypeName": "Пункт р.ш.",
                    "Description": "",
                    "FactoryCode": "00005",
                    "DepartmentCode": 50915,
                    "ModifiedBy": null,
                    "ShouldFilterByDepartmentCode": true,
                    "ValueRange": [
                      {
                        "Code": 20814,
                        "MonitoringTaskCode": 1016534,
                        "EquipmentCode": "",
                        "ReferenceCode": 3133,
                        "CharacteristicCode": 661,
                        "MinValue": 1,
                        "MaxValue": 1,
                        "NormalValue": 1,
                        "ValueCode": 5,
                        "ValueName": "Тривога",
                        "CategoryCode": "4",
                        "CategoryName": "Аварійність",
                        "Status": ""
                      },
                      {
                        "Code": 16103,
                        "MonitoringTaskCode": 1016534,
                        "EquipmentCode": "",
                        "ReferenceCode": 3133,
                        "CharacteristicCode": 661,
                        "MinValue": -1,
                        "MaxValue": -1,
                        "NormalValue": 5,
                        "ValueCode": 4,
                        "ValueName": "Норма",
                        "CategoryCode": "1IM",
                        "CategoryName": "Поліпшення",
                        "Status": ""
                      }
                    ]
                  }
                ],
                "MaintenanceTasks": null,
                "RepairTasks": null
              }
            ]
          },
          {
            "Code": 3049,
            "ParentCode": 933,
            "ModelCode": "Т00009000000001",
            "Name": "Установка 1",
            "FactoryCode": "00005",
            "FactoryName": "Factory5",
            "DepartmentCode": 50915,
            "DepartmentName": "Відділ головного механіка",
            "TechnicalPlaces": null,
            "Equipments": [
              {
                "Code": "BBB1027",
                "TechPlaceCode": 3049,
                "FactoryCode": "00005",
                "TypeCode": "0444",
                "TypeName": "Установка 1",
                "ModelCode": "Т00009000000001",
                "Name": "Установка 1",
                "FullName": "Установка 1",
                "Marking": "",
                "CriticalityLevel": "C2",
                "MonitorDateStart": "2025-03-03T00:00:00+00:00",
                "MonitorFrequencyCode": 3,
                "MonitorFrequency": "Щомісяця",
                "QrCode": null,
                "OdometerDataRequired": false,
                "MonitoringTasks": [
                  {
                    "Code": 1016311,
                    "EquipmentCode": "BBB1027",
                    "TechPlaceCode": 3049,
                    "TechPlaceParentCode": 933,
                    "ModelCode": "Т00009000000001",
                    "ModelName": "Установка 1",
                    "CharacteristicCode": 1131,
                    "CharacteristicName": "Наявність помилки на екрані управлінні",
                    "UnitName": "Візуально",
                    "Value": 0,
                    "IsBool": true,
                    "PlanDate": "2026-05-03T00:00:00+00:00",
                    "FactDate": "0001-01-01T00:00:00+00:00",
                    "EquipmentTypeCode": "0444",
                    "EquipmentTypeName": "Установка 1",
                    "Description": "",
                    "FactoryCode": "00005",
                    "DepartmentCode": 50915,
                    "ModifiedBy": null,
                    "ShouldFilterByDepartmentCode": true,
                    "ValueRange": [
                      {
                        "Code": 30295,
                        "MonitoringTaskCode": 1016311,
                        "EquipmentCode": "97",
                        "ReferenceCode": 7457,
                        "CharacteristicCode": 1131,
                        "MinValue": -1,
                        "MaxValue": -1,
                        "NormalValue": 5,
                        "ValueCode": 4,
                        "ValueName": "Норма",
                        "CategoryCode": "1IM",
                        "CategoryName": "Поліпшення",
                        "Status": ""
                      },
                      {
                        "Code": 30296,
                        "MonitoringTaskCode": 1016311,
                        "EquipmentCode": "97",
                        "ReferenceCode": 7457,
                        "CharacteristicCode": 1131,
                        "MinValue": 1,
                        "MaxValue": 1,
                        "NormalValue": 1,
                        "ValueCode": 5,
                        "ValueName": "Тривога",
                        "CategoryCode": "4",
                        "CategoryName": "Аварійність",
                        "Status": ""
                      },
                      {
                        "Code": 17576,
                        "MonitoringTaskCode": 1016311,
                        "EquipmentCode": "",
                        "ReferenceCode": 3217,
                        "CharacteristicCode": 1131,
                        "MinValue": -1,
                        "MaxValue": -1,
                        "NormalValue": 5,
                        "ValueCode": 4,
                        "ValueName": "Норма",
                        "CategoryCode": "1IM",
                        "CategoryName": "Поліпшення",
                        "Status": ""
                      },
                      {
                        "Code": 22287,
                        "MonitoringTaskCode": 1016311,
                        "EquipmentCode": "",
                        "ReferenceCode": 3217,
                        "CharacteristicCode": 1131,
                        "MinValue": 1,
                        "MaxValue": 1,
                        "NormalValue": 1,
                        "ValueCode": 5,
                        "ValueName": "Тривога",
                        "CategoryCode": "4",
                        "CategoryName": "Аварійність",
                        "Status": ""
                      }
                    ]
                  }
                ],
                "MaintenanceTasks": null,
                "RepairTasks": null
              }
            ]
          },
          {
            "Code": 1983,
            "ParentCode": 933,
            "ModelCode": "Т00099900000001",
            "Name": "Котел газовий 1",
            "FactoryCode": "00005",
            "FactoryName": "Factory5",
            "DepartmentCode": 50915,
            "DepartmentName": "Відділ головного механіка",
            "TechnicalPlaces": null,
            "Equipments": [
              {
                "Code": "BBB536",
                "TechPlaceCode": 1983,
                "FactoryCode": "00005",
                "TypeCode": "0200",
                "TypeName": "Котел газовий",
                "ModelCode": "Т00099900000001",
                "Name": "Котел 1",
                "FullName": "Котел 1",
                "Marking": "V1",
                "CriticalityLevel": "A2",
                "MonitorDateStart": "2025-03-03T00:00:00+00:00",
                "MonitorFrequencyCode": 15,
                "MonitorFrequency": "1 раз на місяць",
                "QrCode": null,
                "OdometerDataRequired": false,
                "MonitoringTasks": [
                  {
                    "Code": 1016404,
                    "EquipmentCode": "BBB536",
                    "TechPlaceCode": 1983,
                    "TechPlaceParentCode": 933,
                    "ModelCode": "Т00099900000001",
                    "ModelName": "Котел 1",
                    "CharacteristicCode": 196,
                    "CharacteristicName": "Відсутність потоку води (помилка на екрані)",
                    "UnitName": "Візуально",
                    "Value": 0,
                    "IsBool": true,
                    "PlanDate": "2026-05-03T00:00:00+00:00",
                    "FactDate": "0001-01-01T00:00:00+00:00",
                    "EquipmentTypeCode": "0200",
                    "EquipmentTypeName": "Котел",
                    "Description": "",
                    "FactoryCode": "00005",
                    "DepartmentCode": 50915,
                    "ModifiedBy": null,
                    "ShouldFilterByDepartmentCode": true,
                    "ValueRange": [
                      {
                        "Code": 22948,
                        "MonitoringTaskCode": 1016407,
                        "EquipmentCode": "",
                        "ReferenceCode": 2919,
                        "CharacteristicCode": 196,
                        "MinValue": 1,
                        "MaxValue": 1,
                        "NormalValue": 1,
                        "ValueCode": 5,
                        "ValueName": "Тривога",
                        "CategoryCode": "4",
                        "CategoryName": "Аварійність",
                        "Status": ""
                      },
                      {
                        "Code": 18237,
                        "MonitoringTaskCode": 1016407,
                        "EquipmentCode": "",
                        "ReferenceCode": 2919,
                        "CharacteristicCode": 196,
                        "MinValue": -1,
                        "MaxValue": -1,
                        "NormalValue": 5,
                        "ValueCode": 4,
                        "ValueName": "Норма",
                        "CategoryCode": "1IM",
                        "CategoryName": "Поліпшення",
                        "Status": ""
                      }
                    ]
                  },
                  {
                    "Code": 1016405,
                    "EquipmentCode": "BBB536",
                    "TechPlaceCode": 1983,
                    "TechPlaceParentCode": 933,
                    "ModelCode": "Т00099900000001",
                    "ModelName": "Котел 1",
                    "CharacteristicCode": 1130,
                    "CharacteristicName": "Наявність помилки на екрані",
                    "UnitName": "Візуально",
                    "Value": 0,
                    "IsBool": true,
                    "PlanDate": "2026-05-03T00:00:00+00:00",
                    "FactDate": "0001-01-01T00:00:00+00:00",
                    "EquipmentTypeCode": "0200",
                    "EquipmentTypeName": "Котел",
                    "Description": "",
                    "FactoryCode": "00005",
                    "DepartmentCode": 50915,
                    "ModifiedBy": null,
                    "ShouldFilterByDepartmentCode": true,
                    "ValueRange": [
                      {
                        "Code": 22949,
                        "MonitoringTaskCode": 1016408,
                        "EquipmentCode": "",
                        "ReferenceCode": 2920,
                        "CharacteristicCode": 1130,
                        "MinValue": 1,
                        "MaxValue": 1,
                        "NormalValue": 1,
                        "ValueCode": 5,
                        "ValueName": "Тривога",
                        "CategoryCode": "4",
                        "CategoryName": "Аварійність",
                        "Status": ""
                      },
                      {
                        "Code": 18238,
                        "MonitoringTaskCode": 1016408,
                        "EquipmentCode": "",
                        "ReferenceCode": 2920,
                        "CharacteristicCode": 1130,
                        "MinValue": -1,
                        "MaxValue": -1,
                        "NormalValue": 5,
                        "ValueCode": 4,
                        "ValueName": "Норма",
                        "CategoryCode": "1IM",
                        "CategoryName": "Поліпшення",
                        "Status": ""
                      }
                    ]
                  },
                  {
                    "Code": 1016406,
                    "EquipmentCode": "BBB536",
                    "TechPlaceCode": 1983,
                    "TechPlaceParentCode": 933,
                    "ModelCode": "Т00099900000001",
                    "ModelName": "Котел 1",
                    "CharacteristicCode": 3124,
                    "CharacteristicName": "Температура теплоносія",
                    "UnitName": "град.С",
                    "Value": 0,
                    "IsBool": false,
                    "PlanDate": "2026-05-03T00:00:00+00:00",
                    "FactDate": "0001-01-01T00:00:00+00:00",
                    "EquipmentTypeCode": "0200",
                    "EquipmentTypeName": "Котел газовий",
                    "Description": "",
                    "FactoryCode": "00005",
                    "DepartmentCode": 50915,
                    "ModifiedBy": null,
                    "ShouldFilterByDepartmentCode": true,
                    "ValueRange": [
                      {
                        "Code": 8236,
                        "MonitoringTaskCode": 1016409,
                        "EquipmentCode": "",
                        "ReferenceCode": 2921,
                        "CharacteristicCode": 3124,
                        "MinValue": 40,
                        "MaxValue": 44,
                        "NormalValue": 3,
                        "ValueCode": 6,
                        "ValueName": "Норма. Профілактичне обслуговування",
                        "CategoryCode": "1PR",
                        "CategoryName": "Попереджувальне обслуговування",
                        "Status": ""
                      },
                      {
                        "Code": 2921,
                        "MonitoringTaskCode": 1016409,
                        "EquipmentCode": "",
                        "ReferenceCode": 2921,
                        "CharacteristicCode": 3124,
                        "MinValue": 45,
                        "MaxValue": 95,
                        "NormalValue": 5,
                        "ValueCode": 4,
                        "ValueName": "Норма",
                        "CategoryCode": "1IM",
                        "CategoryName": "Поліпшення",
                        "Status": ""
                      },
                      {
                        "Code": 13551,
                        "MonitoringTaskCode": 1016409,
                        "EquipmentCode": "",
                        "ReferenceCode": 2921,
                        "CharacteristicCode": 3124,
                        "MinValue": 1,
                        "MaxValue": 39,
                        "NormalValue": 1,
                        "ValueCode": 5,
                        "ValueName": "Тривога",
                        "CategoryCode": "4",
                        "CategoryName": "Аварійність",
                        "Status": ""
                      }
                    ]
                  }
                ],
                "MaintenanceTasks": null,
                "RepairTasks": null
              }
            ]
          },
          {
            "Code": 1984,
            "ParentCode": 933,
            "ModelCode": "Т00000001000002",
            "Name": "Котел газовий 1",
            "FactoryCode": "00005",
            "FactoryName": "Factory5",
            "DepartmentCode": 50915,
            "DepartmentName": "Відділ головного механіка",
            "TechnicalPlaces": null,
            "Equipments": [
              {
                "Code": "BBB537",
                "TechPlaceCode": 1984,
                "FactoryCode": "00005",
                "TypeCode": "0200",
                "TypeName": "Котел газовий",
                "ModelCode": "Т00000001000002",
                "Name": "Котел паровий 2",
                "FullName": "Котел газовий 1",
                "Marking": "V1",
                "CriticalityLevel": "A2",
                "MonitorDateStart": "2025-03-03T00:00:00+00:00",
                "MonitorFrequencyCode": 15,
                "MonitorFrequency": "1 раз на місяць",
                "QrCode": null,
                "OdometerDataRequired": false,
                "MonitoringTasks": [
                  {
                    "Code": 1016407,
                    "EquipmentCode": "BBB537",
                    "TechPlaceCode": 1984,
                    "TechPlaceParentCode": 933,
                    "ModelCode": "Т00000001000002",
                    "ModelName": "Котел газовий 1",
                    "CharacteristicCode": 196,
                    "CharacteristicName": "Відсутність потоку води (помилка на екрані)",
                    "UnitName": "Візуально",
                    "Value": 0,
                    "IsBool": true,
                    "PlanDate": "2026-05-03T00:00:00+00:00",
                    "FactDate": "0001-01-01T00:00:00+00:00",
                    "EquipmentTypeCode": "0200",
                    "EquipmentTypeName": "Котел газовий",
                    "Description": "",
                    "FactoryCode": "00005",
                    "DepartmentCode": 50915,
                    "ModifiedBy": null,
                    "ShouldFilterByDepartmentCode": true,
                    "ValueRange": [
                      {
                        "Code": 22948,
                        "MonitoringTaskCode": 1016407,
                        "EquipmentCode": "",
                        "ReferenceCode": 2919,
                        "CharacteristicCode": 196,
                        "MinValue": 1,
                        "MaxValue": 1,
                        "NormalValue": 1,
                        "ValueCode": 5,
                        "ValueName": "Тривога",
                        "CategoryCode": "4",
                        "CategoryName": "Аварійність",
                        "Status": ""
                      },
                      {
                        "Code": 18237,
                        "MonitoringTaskCode": 1016407,
                        "EquipmentCode": "",
                        "ReferenceCode": 2919,
                        "CharacteristicCode": 196,
                        "MinValue": -1,
                        "MaxValue": -1,
                        "NormalValue": 5,
                        "ValueCode": 4,
                        "ValueName": "Норма",
                        "CategoryCode": "1IM",
                        "CategoryName": "Поліпшення",
                        "Status": ""
                      }
                    ]
                  },
                  {
                    "Code": 1016408,
                    "EquipmentCode": "BBB537",
                    "TechPlaceCode": 1984,
                    "TechPlaceParentCode": 933,
                    "ModelCode": "Т00000001000002",
                    "ModelName": "Котел газовий 1",
                    "CharacteristicCode": 1130,
                    "CharacteristicName": "Наявність помилки на екрані",
                    "UnitName": "Візуально",
                    "Value": 0,
                    "IsBool": true,
                    "PlanDate": "2026-05-03T00:00:00+00:00",
                    "FactDate": "0001-01-01T00:00:00+00:00",
                    "EquipmentTypeCode": "0200",
                    "EquipmentTypeName": "Котел газовий",
                    "Description": "",
                    "FactoryCode": "00005",
                    "DepartmentCode": 50915,
                    "ModifiedBy": null,
                    "ShouldFilterByDepartmentCode": true,
                    "ValueRange": [
                      {
                        "Code": 22949,
                        "MonitoringTaskCode": 1016408,
                        "EquipmentCode": "",
                        "ReferenceCode": 2920,
                        "CharacteristicCode": 1130,
                        "MinValue": 1,
                        "MaxValue": 1,
                        "NormalValue": 1,
                        "ValueCode": 5,
                        "ValueName": "Тривога",
                        "CategoryCode": "4",
                        "CategoryName": "Аварійність",
                        "Status": ""
                      },
                      {
                        "Code": 18238,
                        "MonitoringTaskCode": 1016408,
                        "EquipmentCode": "",
                        "ReferenceCode": 2920,
                        "CharacteristicCode": 1130,
                        "MinValue": -1,
                        "MaxValue": -1,
                        "NormalValue": 5,
                        "ValueCode": 4,
                        "ValueName": "Норма",
                        "CategoryCode": "1IM",
                        "CategoryName": "Поліпшення",
                        "Status": ""
                      }
                    ]
                  },
                  {
                    "Code": 1016409,
                    "EquipmentCode": "BBB537",
                    "TechPlaceCode": 1984,
                    "TechPlaceParentCode": 933,
                    "ModelCode": "Т00000001000002",
                    "ModelName": "Котел газовий 1",
                    "CharacteristicCode": 3124,
                    "CharacteristicName": "Температура теплоносія",
                    "UnitName": "град.С",
                    "Value": 0,
                    "IsBool": false,
                    "PlanDate": "2026-05-03T00:00:00+00:00",
                    "FactDate": "0001-01-01T00:00:00+00:00",
                    "EquipmentTypeCode": "0200",
                    "EquipmentTypeName": "Котел газовий",
                    "Description": "",
                    "FactoryCode": "00005",
                    "DepartmentCode": 50915,
                    "ModifiedBy": null,
                    "ShouldFilterByDepartmentCode": true,
                    "ValueRange": [
                      {
                        "Code": 8236,
                        "MonitoringTaskCode": 1016409,
                        "EquipmentCode": "",
                        "ReferenceCode": 2921,
                        "CharacteristicCode": 3124,
                        "MinValue": 40,
                        "MaxValue": 44,
                        "NormalValue": 3,
                        "ValueCode": 6,
                        "ValueName": "Норма. Профілактичне обслуговування",
                        "CategoryCode": "1PR",
                        "CategoryName": "Попереджувальне обслуговування",
                        "Status": ""
                      },
                      {
                        "Code": 2921,
                        "MonitoringTaskCode": 1016409,
                        "EquipmentCode": "",
                        "ReferenceCode": 2921,
                        "CharacteristicCode": 3124,
                        "MinValue": 45,
                        "MaxValue": 95,
                        "NormalValue": 5,
                        "ValueCode": 4,
                        "ValueName": "Норма",
                        "CategoryCode": "1IM",
                        "CategoryName": "Поліпшення",
                        "Status": ""
                      },
                      {
                        "Code": 13551,
                        "MonitoringTaskCode": 1016409,
                        "EquipmentCode": "",
                        "ReferenceCode": 2921,
                        "CharacteristicCode": 3124,
                        "MinValue": 1,
                        "MaxValue": 39,
                        "NormalValue": 1,
                        "ValueCode": 5,
                        "ValueName": "Тривога",
                        "CategoryCode": "4",
                        "CategoryName": "Аварійність",
                        "Status": ""
                      }
                    ]
                  }
                ],
                "MaintenanceTasks": null,
                "RepairTasks": null
              }
            ]
          }
        ],
        "Equipments": null
      }
    ]
  },
  "Error": null
}